streamsx/kafka/__init__.py
streamsx/kafka/_kafka.py
streamsx/kafka/schema.py
streamsx/kafka/scripts/__init__.py
streamsx/kafka/scripts/makeproperties.py
streamsx.kafka-1.10.2.dist-info/LICENSE.txt
streamsx.kafka-1.10.2.dist-info/METADATA
streamsx.kafka-1.10.2.dist-info/WHEEL
streamsx.kafka-1.10.2.dist-info/entry_points.txt
streamsx.kafka-1.10.2.dist-info/top_level.txt
streamsx.kafka-1.10.2.dist-info/RECORD
